kgr-0.3.0.dist-info/METADATA
kgr-0.3.0.dist-info/WHEEL
kgr-0.3.0.dist-info/licenses/LICENSE
kgr/__init__.py
kgr/__main__.py
kgr/convert.py
kgr/geocode.py
kgr/lib.py
kgr/prepare.py
kgr-0.3.0.dist-info/RECORD
