Metadata-Version: 2.1
Name: kgr
Version: 0.3.0
Summary: Miltitool for convert data from https://memopzk.org to Google Maps
Author-Email: Dmitry Luschan <dluschan@gmail.com>
Maintainer-Email: Dmitry Luschan <dluschan@gmail.com>
License: MIT License
Classifier: Development Status :: 4 - Beta
Classifier: License :: OSI Approved :: MIT License
Classifier: Programming Language :: Python :: 3
Classifier: Operating System :: OS Independent
Classifier: Topic :: Utilities
Classifier: Environment :: Console
Project-URL: Homepage, https://github.com/dluschan/kgr
Project-URL: Repository, https://github.com/dluschan/kgr.git
Project-URL: Issues, https://github.com/dluschan/kgr/issues
Requires-Dist: requests
Requires-Dist: geopy
Requires-Dist: bs4
